{
  "slug": "kluz-peace-prize-2023",
  "brow": "Event",
  "title": "Kluz Prize for PeaceTech 2023",
  "heading": "Kluz Prize for PeaceTech 2023",
  "tagline": "Celebrating those who build peace",
  "year": 2023,
  "images": [
    "/assets/images/events/2023/kluz-peace-tech-prize-2023-09.jpg",
    "/assets/images/events/2023/kluz-peace-tech-prize-2023-03.jpg",
    "/assets/images/events/2023/kluz-peace-tech-prize-2023-05.jpg",
    "/assets/images/events/2023/kluz-peace-tech-prize-2023-07.jpg",
    "/assets/images/events/2023/kluz-peace-tech-prize-2023-08.jpg",
    "/assets/images/events/2023/kluz-peace-tech-prize-2023-10.jpg"
  ],
  "cover_image": "/assets/images/events/2023/kluz-peace-tech-prize-2023-03.jpg",
  "winners": {
    "overview": "<p>The 2023 Kluz Prize for PeaceTech was awarded to Bogdan Ivanel, Founder and Chairperson of Commit Global. Three Special Distinctions were awarded to Ishraq Irteza (Deployment Strategist at Palantir Technologies’ Foundry) for Big Tech Building Peace, Megan Price (Executive Director of Human Rights Data Analysis Group) for a Non Profit Organization Advancing Peace, and Shawn Guttman (Co-Founder and CEO of Project Didi) for Innovative Use of AI/ML.</p><p>The 2023 Kluz Prize for PeaceTech was organized by Kluz Ventures with the support of The GovLab and awarded in September 2023, on the eve of the International Day of Peace during the 78th United Nations General Assembly. The Award Ceremony was held at the Union League Club in New York City.</p>",
    "winner": {
      "name": "Commit Global",
      "prize": "winner",
      "slug": "commit-global",
      "logo": "/assets/images/winners/commit-global-logo.png"
    },
    "ai_ml": {
      "name": "Project Didi",
      "prize": "Innovative Use of AI/ML",
      "slug": "project-didi",
      "logo": "/assets/images/winners/project-didi-logo.webp"
    },
    "big_tech": {
      "name": "Palantir Foundry",
      "prize": "Big Tech Building Peace",
      "slug": "palantir-foundry",
      "logo": "/assets/images/winners/palantir-logo.png"
    },
    "non_profit": {
      "name": "Human Rights Data Analysis Group",
      "prize": "Non Profit Organization Advancing Peace",
      "slug": "human-rights-analysis-group",
      "logo": "/assets/images/winners/human-rights-analysis-group-logo.png"
    }
  },
  "jury": [
    {
      "name": "Ana Carolina González Peña",
      "title": "Vice President of Research and Analysis at Direct Relief",
      "image": "/assets/images/jury/ana-carolina-gonzalez-pena.jpg",
      "url": "https://www.linkedin.com/in/anacaro26/"
    },
    {
      "name": "Artur Kluz",
      "title": "Founder & CEO of Kluz Ventures",
      "image": "/assets/images/jury/artur-kluz.jpg",
      "url": "https://www.linkedin.com/in/akluz"
    },
    {
      "name": "Bradley Tusk",
      "title": "Co-Founder & Managing Partner of Tusk Venture Partners, Founder of Tusk Strategies",
      "image": "/assets/images/jury/bradley-tusk.jpg",
      "url": "https://www.bradleytusk.com/"
    },
    {
      "name": "Chris Larsen",
      "title": "Angel Investor and Business Executive",
      "image": "/assets/images/jury/chris-larsen.webp",
      "url": "https://en.m.wikipedia.org/wiki/Chris_Larsen"
    },
    {
      "name": "Daniel Wilhelm",
      "title": "President of The Harry Frank Guggenheim Foundation",
      "image": "/assets/images/jury/daniel-wilhelm.jpg",
      "url": "https://www.linkedin.com/in/danielfwilhelm/"
    },
    {
      "name": "Evelyn Tauchnitz",
      "title": "Senior Research Fellow at the University of Lucerne’s Institute of Social Ethics",
      "image": "/assets/images/jury/evelyne-tauchnitz.jpg",
      "url": "https://linkedin.com/in/evelyne-tauchnitz-0a2a637"
    },
    {
      "name": "Kay Firth-Butterfield",
      "title": "Executive Director of the Centre for Trustworthy Technology ",
      "image": "/assets/images/jury/kay-firth-butterfield.png",
      "url": "https://en.m.wikipedia.org/wiki/Kay_Firth-Butterfield"
    },
    {
      "name": "Simona Paravani-Mellinghoff",
      "title": "Global CIO of Solutions - Multi-Asset Strategies & Solutions at BlackRock",
      "image": "/assets/images/jury/simona-paravani-mellinghoff.jpg",
      "url": "https://linkedin.com/in/simona-paravani-cfa-5129524"
    },
    {
      "name": "Stefaan Verhulst",
      "title": "Co-Founder & Chief Research & Development Officer of The GovLab ",
      "image": "/assets/images/jury/stefaan-verhulst.jpg",
      "url": "https://www.linkedin.com/in/stefaan-verhulst"
    },
    {
      "name": "Stephen Roberts",
      "title": "Professor of Machine Learning at University of Oxford & Co-Founder of Mind Foundry",
      "image": "/assets/images/jury/stephen-roberts.jpg",
      "url": "https://linkedin.com/in/stephen-roberts-b0985a17"
    },
    {
      "name": "Stuart E. Eizenstat",
      "title": "Senior Counsel at Covington & Burling",
      "image": "/assets/images/jury/stuart-eizenstat.webp",
      "url": "https://en.m.wikipedia.org/wiki/Stuart_E._Eizenstat"
    }
  ]
}
